magma_seismic/__init__.py
magma_seismic/const.py
magma_seismic/download.py
magma_seismic/magma_seismic.py
magma_seismic/plot.py
magma_seismic/utils.py
magma_seismic-0.0.6.dist-info/licenses/LICENSE
magma_seismic-0.0.6.dist-info/WHEEL
magma_seismic-0.0.6.dist-info/METADATA
magma_seismic-0.0.6.dist-info/RECORD
