Metadata-Version: 2.4
Name: magma-seismic
Version: 0.0.6
Summary: MAGMA Seismic
Keywords: magma,indonesia,volcano,seismic
Author-email: Martanto <martanto@live.com>, Devy Kamil Syahbana <devy.syahbana@gmail.com>, Syarif Abdul Manaf <riefmof@gmail.com>
Requires-Python: >=3.11
Classifier: License :: OSI Approved :: MIT License
Classifier: Operating System :: OS Independent
Classifier: Programming Language :: Python :: 3.11
Classifier: Programming Language :: Python :: 3.12
License-File: LICENSE
Requires-Dist: obspy>=1.4.2
Requires-Dist: openpyxl>=3.1.5
Requires-Dist: pandas>=2.2.2
Requires-Dist: numpy>=2.2.5
Requires-Dist: isort ; extra == "dev"
Requires-Dist: black[d] ; extra == "dev"
Requires-Dist: obspy ; extra == "dev"
Requires-Dist: openpyxl ; extra == "dev"
Requires-Dist: pandas ; extra == "dev"
Requires-Dist: numpy ; extra == "dev"
Project-URL: Homepage, https://github.com/martanto/magma-seismic
Project-URL: Issues, https://github.com/martanto/magma-seismic/issues
Provides-Extra: dev
